LICENCE.txt
MANIFEST.in
README.rst
setup.py
django_feedparser/__init__.py
django_feedparser/models.py
django_feedparser/renderer.py
django_feedparser/settings.py
django_feedparser/urls.py
django_feedparser/utils.py
django_feedparser/views.py
django_feedparser.egg-info/PKG-INFO
django_feedparser.egg-info/SOURCES.txt
django_feedparser.egg-info/dependency_links.txt
django_feedparser.egg-info/not-zip-safe
django_feedparser.egg-info/requires.txt
django_feedparser.egg-info/top_level.txt
django_feedparser/templates/django_feedparser/basic_feed_renderer.html
django_feedparser/templates/django_feedparser/view.html
django_feedparser/templatetags/__init__.py
django_feedparser/templatetags/feedparser_tags.py