Metadata-Version: 1.1
Name: django-feedparser
Version: 0.2.1
Summary: 
